gasblowdowncalculator/__init__.py
gasblowdowncalculator/dataModelCalculation.py
gasblowdowncalculator/gasblowdowncalculator.py
gasblowdowncalculator/simulation.py
gasblowdowncalculator/calculation/__init__.py
gasblowdowncalculator/calculation/acc_LibBlowdownCalc.py
gasblowdowncalculator/calculation/acc_LibBwrCalc.py
gasblowdowncalculator/calculation/acc_util.py
gasblowdowncalculator/gas/__init__.py
gasblowdowncalculator/gas/gasComposition.py
gasblowdowncalculator/gas/gasData.py
gasblowdowncalculator/gas/gasPieChart.py
gasblowdowncalculator/results/__init__.py
gasblowdowncalculator/results/results.py
gasblowdowncalculator/ui/__init__.py
gasblowdowncalculator/ui/ui_MainWindow.py
gasblowdowncalculator-0.0.5.dist-info/LICENSE
gasblowdowncalculator-0.0.5.dist-info/METADATA
gasblowdowncalculator-0.0.5.dist-info/WHEEL
gasblowdowncalculator-0.0.5.dist-info/entry_points.txt
gasblowdowncalculator-0.0.5.dist-info/top_level.txt
gasblowdowncalculator-0.0.5.dist-info/RECORD
