Metadata-Version: 2.1
Name: gasblowdowncalculator
Version: 0.0.5
Summary: GasBlowdownCalculator
Home-page: UNKNOWN
Author: Michael Fischer
Author-email: mfischer.sw@gmail.com
License: UNKNOWN
Project-URL: Source, https://github.com/mfischersw/GasBlowdownCalculator/
Platform: UNKNOWN
Requires-Python: >=3.7, <4
License-File: LICENSE
